{
  "schemaVersion": 1,
  "siteRoot": "https://sawyerhouse-music.b-cdn.net",
  "artistSlug": "sawyerhouse-music",
  "artistName": "Ben Sawyer",
  "id": "fa9deda8-7d7e-4b7b-afbf-ee869d4e5764",
  "slug": "afterlight-deep-glitch-bounce-mix",
  "title": "Afterlight (Deep Glitch Bounce Mix)",
  "album": "",
  "year": "2025",
  "caption": "I was inspired to make this by my son",
  "about": "My son wanted me to try and make some stutter house. I was currently on a kick to do songs with interesting words in the hooks even made up ones. The result is this song.",
  "lyrics": "[Instrumental 2 bars]\n\n[VERSE 1]\nAfter a flash\nAfter lightning turns sand to glass\nAfter the sun\nUntil the moon \nEvery time I close my eyes\nAnd still see you…\n(you, you, you, you, you)\n\n[CHORUS 1]\nAfter-after-afterlight... light-light-light\nAfter-after-afterlight... light-light-light\nWhere we were... we-we-were... \nWhere we might... mi-mi-might\nAfter-after-afterlight\n\n[VERSE 2]\nAfter stars shine\nAfter supernovas turn suns to life\nBeyond sunset\nBefore midnight\nEvery time I close my eyes\nAnd still see you…\n(you, you, you, you, you)\n\n[CHORUS 2]\nAfter-after-afterlight... light-light-light\nAfter-after-afterlight... light-light-light\nWhere we were... we-we-were...\nWhere we might... mi-mi-might\nAfter-after-afterlight\n\n[Instrumental 2 bars]\n\n [Outro]\nEvery time I close my eyes\nAnd still see you…\n(you, you, you, you, you)\nNot morning\nNot night\nJust... after-after-afterlight\nWhere we were... we-we-were\nWhere we might... mi-mi-might\n\n[Instrumental 4 bars]\n\n[Fade]\nAfter-after-afterlight... light-light-light\nAfter-after-afterlight... light-light-light\nWhere we were... we-we-were... where we might... mi-mi-might\nAfter-after-afterlight",
  "coverUrl": "cover.jpg",
  "extraImageUrl": null,
  "pageUrl": "../afterlight-deep-glitch-bounce-mix.html",
  "playbackUrl": "manifest.m3u8",
  "streamLinks": {
    "youtube": "",
    "spotify": "",
    "soundcloud": ""
  },
  "playbackScope": "full",
  "playbackQuality": "high",
  "buildVersion": "20260629T184514Z-e098071"
}
